django_sortable_tabular/__init__.py
django_sortable_tabular/admin.py
django_sortable_tabular/static/django_sortable_tabular/sortable_tabular.js
django_sortable_tabular-0.1.1.dist-info/LICENSE
django_sortable_tabular-0.1.1.dist-info/METADATA
django_sortable_tabular-0.1.1.dist-info/WHEEL
django_sortable_tabular-0.1.1.dist-info/top_level.txt
django_sortable_tabular-0.1.1.dist-info/RECORD
