Metadata-Version: 2.1
Name: django_sortable_tabular
Version: 0.1.1
Summary: A Django library for sortable TabularInline in admin interface
Home-page: https://github.com/michalkonwiak/django_sortable_tabular
Author: Michał Konwiak
Classifier: Framework :: Django
Classifier: Programming Language :: Python :: 3
License-File: LICENSE
Requires-Dist: django >=3.2
